pip_help/__init__.py
pip_help/main.py
pip_help/pip_func.py
pip_help-1.0.3.1.dist-info/METADATA
pip_help-1.0.3.1.dist-info/WHEEL
pip_help-1.0.3.1.dist-info/entry_points.txt
pip_help-1.0.3.1.dist-info/RECORD
