Metadata-Version: 2.4
Name: pip-help
Version: 1.0.3.1
Summary: pip-help is a command line tool for temporarily installing packages.
Project-URL: Source, https://github.com/ilokeshpawar/pip-help
Author-email: Lokesh Pawar <ilokeshpawar@gmail.com>
Requires-Python: >=3.10
Requires-Dist: requests>=2.32.3
